Workbook

Sheet Parâmetros
A1: Parâmetros da operação
A2: Ênio Toldos (ShopLima) — modelo da planilha markup JB
A4: Item | B4: Valor | C4: De onde veio
A5: Margem mínima do Ênio | B5: 0.12 | C5: Piso de lucro que ele aceita. NÃO é taxa do Mercado Livre.
A6: Alíquota de imposto | B6: 0.05 | C6: Informado pelo Ênio: 5% sobre o valor de venda.
A8: A fórmula é a do JB, sem alteração
A9: Lucro Líquido = (Venda + Rebate) − ((Venda + Rebate) × Taxa) − Custo − Manuseio − Frete
A10: Porcentagem = Lucro Líquido ÷ (Venda + Rebate)
A12: Uma diferença em relação à planilha do JB
A13: No JB a 'Taxa da Plataforma' é um número só — 20% numa conta, 27,5% na outra.
A14: Aqui ela continua sendo UM número na fórmula, mas é montada por soma de duas
A15: parcelas visíveis: a comissão que o Mercado Livre cobra DAQUELE anúncio, medida
A16: uma a uma, e os 5% de imposto. Elas ficam em colunas próprias para poderem ser
A17: conferidas — a comissão do ML varia por categoria e vai de 10,5% a 16,5% nesta
A18: conta, então um número redondo esconderia 6 pontos de diferença.
A20: Colunas herdadas do JB que ainda estão zeradas aqui
A21: Rebate ..... subsídio que a plataforma devolve. Entra somado à venda, e a taxa
... A27: Enquanto Frete e Manuseio estiverem zerados, todo lucro desta planilha está OTIMISTA.

Sheet Operação
A1: Operação — lucro por anúncio
A2: Mesma conta da planilha markup JB. Preencha Rebate, Manuseio e Frete; o resto se recalcula.
A4: Conta | B4: MLB | C4: Anúncio | D4: Valor de Venda | E4: Custo do Produto | F4: Comissão ML (%) | G4: Imposto (%) | H4: Taxa da Plataforma (%) | I4: Rebate | J4: Manuseio | K4: Frete | L4: Lucro Líquido | M4: Porcentagem | N4: Venda mínima p/ 12% | O4: Situação
A5: enio | B5: MLB4719594491 | C5: Toldo Policarbonato 155x100 (madeira) | D5: 619.99 | E5: 288 | F5: 0.165 | G5: =Parâmetros!$B$6 -> 0.05 | H5: =F5+G5 -> 0.215 | I5: 0 | J5: 0 | K5: 0 | L5: =(D5+I5)-((D5+I5)*H5)-E5-J5-K5 -> 198.69215 | M5: =IFERROR(L5*100/(D5+I5),"") -> 32.047638 | N5: =IFERROR((E5+J5+K5)/(1-H5-Parâmetros!$B$5)-I5,"") -> 433.08271 | O5: =IF(L5<0,"PREJUÍZO",IF(D5<N5,"ABAIXO DO PISO","OK")) -> OK
A6: enio | B6: MLB4722895661 | C6: Toldo Policarbonato 380x100 (madeira) | D6: 1490.99 | E6: 639 | F6: 0.165 | G6: =Parâmetros!$B$6 -> 0.05 | H6: =F6+G6 -> 0.215 | I6: 0 | J6: 0 | K6: 0 | L6: =(D6+I6)-((D6+I6)*H6)-E6-J6-K6 -> 531.42715 | M6: =IFERROR(L6*100/(D6+I6),"") -> 35.64257 | N6: =IFERROR((E6+J6+K6)/(1-H6-Parâmetros!$B$5)-I6,"") -> 960.90226 | O6: =IF(L6<0,"PREJUÍZO",IF(D6<N6,"ABAIXO DO PISO","OK")) -> OK
A7: enio | B7: MLB6864833186 | C7: Toldo Policarbonato 305x100 (madeira) | D7: 1380.99 | E7: 521 | F7: 0.165 | G7: =Parâmetros!$B$6 -> 0.05 | H7: =F7+G7 -> 0.215 | I7: 0 | J7: 0 | K7: 0 | L7: =(D7+I7)-((D7+I7)*H7)-E7-J7-K7 -> 563.07715 | M7: =IFERROR(L7*100/(D7+I7),"") -> 40.773442 | N7: =IFERROR((E7+J7+K7)/(1-H7-Parâmetros!$B$5)-I7,"") -> 783.45865 | O7: =IF(L7<0,"PREJUÍZO",IF(D7<N7,"ABAIXO DO PISO","OK")) -> OK
A8: enio | B8: MLB4693629595 | C8: Toldo Policarbonato 230x100 (madeira) | D8: 890.99 | E8: 408 | F8: 0.165 | G8: =Parâmetros!$B$6 -> 0.05 | H8: =F8+G8 -> 0.215 | I8: 0 | J8: 0 | K8: 0 | L8: =(D8+I8)-((D8+I8)*H8)-E8-J8-K8 -> 291.42715 | M8: =IFERROR(L8*100/(D8+I8),"") -> 32.70824 | N8: =IFERROR((E8+J8+K8)/(1-H8-Parâmetros!$B$5)-I8,"") -> 613.53383 | O8: =IF(L8<0,"PREJUÍZO",IF(D8<N8,"ABAIXO DO PISO","OK")) -> OK
A9: enio | B9: MLB4728109795 | C9: Toldo Metal 220x70 | D9: 437.99 | E9: 258 | F9: 0.135 | G9: =Parâmetros!$B$6 -> 0.05 | H9: =F9+G9 -> 0.185 | I9: 0 | J9: 0 | K9: 0 | L9: =(D9+I9)-((D9+I9)*H9)-E9-J9-K9 -> 98.96185 | M9: =IFERROR(L9*100/(D9+I9),"") -> 22.594546 | N9: =IFERROR((E9+J9+K9)/(1-H9-Parâmetros!$B$5)-I9,"") -> 371.22302 | O9: =IF(L9<0,"PREJUÍZO",IF(D9<N9,"ABAIXO DO PISO","OK")) -> OK
A10: enio | B10: MLB4728168353 | C10: Toldo Metal 290x70 | D10: 403.99 | E10: 311 | F10: 0.135 | G10: =Parâmetros!$B$6 -> 0.05 | H10: =F10+G10 -> 0.185 | I10: 0 | J10: 0 | K10: 0 | L10: =(D10+I10)-((D10+I10)*H10)-E10-J10-K10 -> 18.25185 | M10: =IFERROR(L10*100/(D10+I10),"") -> 4.5178965 | N10: =IFERROR((E10+J10+K10)/(1-H10-Parâmetros!$B$5)-I10,"") -> 447.48201 | O10: =IF(L10<0,"PREJUÍZO",IF(D10<N10,"ABAIXO DO PISO","OK")) -> ABAIXO DO PISO
A11: enio | B11: MLB6879345124 | C11: Toldo Metal 145x70 | D11: 280.99 | E11: 198 | F11: 0.135 | G11: =Parâmetros!$B$6 -> 0.05 | H11: =F11+G11 -> 0.185 | I11: 0 | J11: 0 | K11: 0 | L11: =(D11+I11)-((D11+I11)*H11)-E11-J11-K11 -> 31.00685 | M11: =IFERROR(L11*100/(D11+I11),"") -> 11.034859 | N11: =IFERROR((E11+J11+K11)/(1-H11-Parâmetros!$B$5)-I11,"") -> 284.89209 | O11: =IF(L11<0,"PREJUÍZO",IF(D11<N11,"ABAIXO DO PISO","OK")) -> ABAIXO DO PISO
A12: enio | B12: MLB4728439145 | C12: Toldo Metal 365x70 | D12: 476.99 | E12: 368 | F12: 0.135 | G12: =Parâmetros!$B$6 -> 0.05 | H12: =F12+G12 -> 0.185 | I12: 0 | J12: 0 | K12: 0 | L12: =(D12+I12)-((D12+I12)*H12)-E12-J12-K12 -> 20.74685 | M12: =IFERROR(L12*100/(D12+I12),"") -> 4.3495356 | N12: =IFERROR((E12+J12+K12)/(1-H12-Parâmetros!$B$5)-I12,"") -> 529.4964 | O12: =IF(L12<0,"PREJUÍZO",IF(D12<N12,"ABAIXO DO PISO","OK")) -> ABAIXO DO PISO
A13: enio | B13: MLB4951921009 | C13: Rack New Aurora Pérola | D13: 897.99 | E13: 274 | F13: 0.115 | G13: =Parâmetros!$B$6 -> 0.05 | H13: =F13+G13 -> 0.165 | I13: 0 | J13: 0 | K13: 0 | L13: =(D13+I13)-((D13+I13)*H13)-E13-J13-K13 -> 475.82165 | M13: =IFERROR(L13*100/(D13+I13),"") -> 52.987411 | N13: =IFERROR((E13+J13+K13)/(1-H13-Parâmetros!$B$5)-I13,"") -> 383.21678 | O13: =IF(L13<0,"PREJUÍZO",IF(D13<N13,"ABAIXO DO PISO","OK")) -> OK
A14: enio | B14: MLB6887673448 | C14: Toldo 230x100 Madeira Bronze | D14: 890.99 | E14: 408 | F14: 0.115 | G14: =Parâmetros!$B$6 -> 0.05 | H14: =F14+G14 -> 0.165 | I14: 0 | J14: 0 | K14: 0 | L14: =(D14+I14)-((D14+I14)*H14)-E14-J14-K14 -> 335.97665 | M14: =IFERROR(L14*100/(D14+I14),"") -> 37.70824 | N14: =IFERROR((E14+J14+K14)/(1-H14-Parâmetros!$B$5)-I14,"") -> 570.62937 | O14: =IF(L14<0,"PREJUÍZO",IF(D14<N14,"ABAIXO DO PISO","OK")) -> OK
A15: enio | B15: MLB4731310629 | C15: Toldo Shoplima 230x100 Preto | D15: 890.99 | E15: 408 | F15: 0.115 | G15: =Parâmetros!$B$6 -> 0.05 | H15: =F15+G15 -> 0.165 | I15: 0 | J15: 0 | K15: 0 | L15: =(D15+I15)-((D15+I15)*H15)-E15-J15-K15 -> 335.97665 | M15: =IFERROR(L15*100/(D15+I15),"") -> 37.70824 | N15: =IFERROR((E15+J15+K15)/(1-H15-Parâmetros!$B$5)-I15,"") -> 570.62937 | O15: =IF(L15<0,"PREJUÍZO",IF(D15<N15,"ABAIXO DO PISO","OK")) -> OK
A16: enio | B16: MLB6926100860 | C16: Toldo 155x100 Madeira Bronze | D16: 619.99 | E16: 288 | F16: 0.115 | G16: =Parâmetros!$B$6 -> 0.05 | H16: =F16+G16 -> 0.165 | I16: 0 | J16: 0 | K16: 0 | L16: =(D16+I16)-((D16+I16)*H16)-E16-J16-K16 -> 229.69165 | M16: =IFERROR(L16*100/(D16+I16),"") -> 37.047638 | N16: =IFERROR((E16+J16+K16)/(1-H16-Parâmetros!$B$5)-I16,"") -> 402.7972 | O16: =IF(L16<0,"PREJUÍZO",IF(D16<N16,"ABAIXO DO PISO","OK")) -> OK
... A32: enio | B32: MLB4793450555 | C32: Mesa Alta Bistrô Tabaco | D32: 245.99 | E32: 117.4 | F32: 0.105 | G32: =Parâmetros!$B$6 -> 0.05 | H32: =F32+G32 -> 0.155 | I32: 0 | J32: 0 | K32: 0 | L32: =(D32+I32)-((D32+I32)*H32)-E32-J32-K32 -> 90.46155 | M32: =IFERROR(L32*100/(D32+I32),"") -> 36.774483 | N32: =IFERROR((E32+J32+K32)/(1-H32-Parâmetros!$B$5)-I32,"") -> 161.93103 | O32: =IF(L32<0,"PREJUÍZO",IF(D32<N32,"ABAIXO DO PISO","OK")) -> OK
C33: TOTAL / MÉDIA | L33: =SUM(L5:L32) -> 6478.1179 | M33: =IFERROR(SUM(L5:L32)*100/(SUM(D5:D32)+SUM(I5:I32)),"") -> 33.143409
C35: Legenda
C36: Azul | D36: medido ou informado — troque só se souber que mudou
C37: Amarelo | D37: PARA PREENCHER — Rebate, Manuseio e Frete
C38: Preto | D38: fórmula, não edite
C39: Verde | D39: puxado da aba Parâmetros
