Workbook

Sheet Resumo
A1: Ênio Toldos (ShopLima) — situação de preço
A2: 28 anúncios ativos · dados de 26/08/2026 · frete ainda não medido
A4: Indicador | B4: Valor
A5: Anúncios ativos analisados | B5: =COUNTA(Precificação!A5:A32) -> 28
A6: Vendendo com margem abaixo de 12% | B6: =COUNTIF(Precificação!P5:P32,"ABAIXO DO PISO")+COUNTIF(Precificação!P5:P32,"PREJUÍZO") -> 7
A7: Vendendo com prejuízo | B7: =COUNTIF(Precificação!P5:P32,"PREJUÍZO") -> 0
A8: Margem média da conta (ponderada por preço) | B8: =Precificação!N33 -> 0.33143409
A9: Comissão média do Mercado Livre | B9: =IF(SUM(Precificação!G5:G32)=0,0,SUM(Precificação!J5:J32)/SUM(Precificação!G5:G32)) -> 0.12585446
A10: Desconto médio aplicado sobre a tabela | B10: =IF(SUM(Precificação!F5:F32)=0,0,1-SUM(Precificação!G5:G32)/SUM(Precificação!F5:F32)) -> 0.23134654
A12: Os cinco anúncios com menor margem hoje
A13: Anúncio | B13: Preço | C13: Sobra | D13: Margem
A14: =Precificação!B12 -> Toldo Metal 365x70 | B14: =Precificação!G12 -> 476.99 | C14: =Precificação!M12 -> 20.74685 | D14: =Precificação!N12 -> 0.043495356
A15: =Precificação!B10 -> Toldo Metal 290x70 | B15: =Precificação!G10 -> 403.99 | C15: =Precificação!M10 -> 18.25185 | D15: =Precificação!N10 -> 0.045178965
A16: =Precificação!B22 -> Toldo Sunny 365x70 Fumê | B16: =Precificação!G22 -> 476.99 | C16: =Precificação!M22 -> 35.05655 | D16: =Precificação!N22 -> 0.073495356
A17: =Precificação!B23 -> Toldo Sunny 365x70 Bronze | B17: =Precificação!G23 -> 476.99 | C17: =Precificação!M23 -> 35.05655 | D17: =Precificação!N23 -> 0.073495356
A18: =Precificação!B24 -> Toldo Sunny 290x70 Bronze | B18: =Precificação!G24 -> 403.99 | C18: =Precificação!M24 -> 30.37155 | D18: =Precificação!N24 -> 0.075178965
A19: Seleção feita com o frete zerado. Preenchido o frete a ordem muda — use o filtro da aba Precificação.
A21: O que esta planilha responde
A22: 1. Quanto o Mercado Livre realmente cobra de cada anúncio — medido, não estimado.
A23: 2. Quanto sobra por venda, ao preço que o comprador está vendo hoje.
A24: 3. Até onde dá para baixar o preço sem furar a margem mínima de 12%.
A26: A aba Conferência abre a conta de uma linha passo a passo, para checar à mão.
A28: O que falta: o custo do frete grátis. Os 28 anúncios têm frete grátis e quem
A29: paga é o vendedor. Preencha a coluna amarela e os números acima passam a valer
A30: de verdade. Enquanto ela estiver zerada, toda margem aqui está OTIMISTA.

Sheet Parâmetros
A1: Parâmetros da precificação
A2: Ênio Toldos (ShopLima) — conta enio-toldos-principal
A4: Item | B4: Valor | C4: De onde veio
A5: Margem mínima do Ênio (piso) | B5: 0.12 | C5: NÃO é taxa do Mercado Livre. É o lucro mínimo que ele aceita. Informado por ele em 27/08/2026.
A6: Alíquota de imposto | B6: 0.05 | C6: Informado pelo Ênio: 5% sobre o preço de venda.
A8: A comissão do Mercado Livre NÃO está aqui. Ela varia por anúncio (10,5% a 16,5%) e fica na coluna D da aba Precificação.
A10: Como o piso é calculado
A11: piso = (custo + frete + taxa fixa) ÷ (1 − comissão ML − imposto − margem)
A13: É o menor preço que ainda entrega a margem mínima. Vender abaixo dele não
A14: é vender com pouco lucro: é vender com lucro menor que o combinado — e
A15: abaixo do custo quando a margem fica negativa.
A17: Origem de cada número
A18: Comissão ML ....... medida anúncio por anúncio em /sites/MLB/listing_prices,
A19: em 26/08/2026. Não é estimativa: é o que o ML cobra.
A20: Taxa fixa ......... medida junto. Só incide em item de preço baixo;
A21: veio zerada nos 28 anúncios.
A22: Preço de vitrine .. o preço que o comprador vê, coletado em 26/08 às 23:39.
... A27: Os 28 anúncios têm frete grátis: quem paga é o Ênio.

Sheet Precificação
A1: Precificação por anúncio
A2: Preencha a coluna FRETE (amarela) com o que o Mercado Livre cobra do vendedor. Todo o resto se recalcula sozinho.
A4: MLB | B4: Anúncio | C4: Tipo | D4: Comissão ML % | E4: Taxa fixa R$ | F4: Preço tabela | G4: Preço vitrine | H4: Custo | I4: Frete | J4: Comissão R$ | K4: Imposto R$ | L4: Total descontado | M4: Sobra | N4: Margem | O4: Piso | P4: Situação
A5: MLB4719594491 | B5: Toldo Policarbonato 155x100 (madeira) | C5: Premium | D5: 0.165 | E5: 0 | F5: 700.9 | G5: 619.99 | H5: 288 | I5: 0 | J5: =G5*D5+E5 -> 102.29835 | K5: =G5*Parâmetros!$B$6 -> 30.9995 | L5: =J5+K5 -> 133.29785 | M5: =G5-L5-H5-I5 -> 198.69215 | N5: =IF(G5=0,0,M5/G5) -> 0.32047638 | O5: =IF((1-D5-Parâmetros!$B$6-Parâmetros!$B$5)<=0,"",(H5+I5+E5)/(1-D5-Parâmetros!$B$6-Parâmetros!$B$5)) -> 433.08271 | P5: =IF(M5<0,"PREJUÍZO",IF(N5<Parâmetros!$B$5,"ABAIXO DO PISO","OK")) -> OK
A6: MLB4722895661 | B6: Toldo Policarbonato 380x100 (madeira) | C6: Premium | D6: 0.165 | E6: 0 | F6: 1700.9 | G6: 1490.99 | H6: 639 | I6: 0 | J6: =G6*D6+E6 -> 246.01335 | K6: =G6*Parâmetros!$B$6 -> 74.5495 | L6: =J6+K6 -> 320.56285 | M6: =G6-L6-H6-I6 -> 531.42715 | N6: =IF(G6=0,0,M6/G6) -> 0.3564257 | O6: =IF((1-D6-Parâmetros!$B$6-Parâmetros!$B$5)<=0,"",(H6+I6+E6)/(1-D6-Parâmetros!$B$6-Parâmetros!$B$5)) -> 960.90226 | P6: =IF(M6<0,"PREJUÍZO",IF(N6<Parâmetros!$B$5,"ABAIXO DO PISO","OK")) -> OK
A7: MLB6864833186 | B7: Toldo Policarbonato 305x100 (madeira) | C7: Premium | D7: 0.165 | E7: 0 | F7: 1600.99 | G7: 1380.99 | H7: 521 | I7: 0 | J7: =G7*D7+E7 -> 227.86335 | K7: =G7*Parâmetros!$B$6 -> 69.0495 | L7: =J7+K7 -> 296.91285 | M7: =G7-L7-H7-I7 -> 563.07715 | N7: =IF(G7=0,0,M7/G7) -> 0.40773442 | O7: =IF((1-D7-Parâmetros!$B$6-Parâmetros!$B$5)<=0,"",(H7+I7+E7)/(1-D7-Parâmetros!$B$6-Parâmetros!$B$5)) -> 783.45865 | P7: =IF(M7<0,"PREJUÍZO",IF(N7<Parâmetros!$B$5,"ABAIXO DO PISO","OK")) -> OK
A8: MLB4693629595 | B8: Toldo Policarbonato 230x100 (madeira) | C8: Premium | D8: 0.165 | E8: 0 | F8: 1246.99 | G8: 890.99 | H8: 408 | I8: 0 | J8: =G8*D8+E8 -> 147.01335 | K8: =G8*Parâmetros!$B$6 -> 44.5495 | L8: =J8+K8 -> 191.56285 | M8: =G8-L8-H8-I8 -> 291.42715 | N8: =IF(G8=0,0,M8/G8) -> 0.3270824 | O8: =IF((1-D8-Parâmetros!$B$6-Parâmetros!$B$5)<=0,"",(H8+I8+E8)/(1-D8-Parâmetros!$B$6-Parâmetros!$B$5)) -> 613.53383 | P8: =IF(M8<0,"PREJUÍZO",IF(N8<Parâmetros!$B$5,"ABAIXO DO PISO","OK")) -> OK
A9: MLB4728109795 | B9: Toldo Metal 220x70 | C9: Premium | D9: 0.135 | E9: 0 | F9: 520 | G9: 437.99 | H9: 258 | I9: 0 | J9: =G9*D9+E9 -> 59.12865 | K9: =G9*Parâmetros!$B$6 -> 21.8995 | L9: =J9+K9 -> 81.02815 | M9: =G9-L9-H9-I9 -> 98.96185 | N9: =IF(G9=0,0,M9/G9) -> 0.22594546 | O9: =IF((1-D9-Parâmetros!$B$6-Parâmetros!$B$5)<=0,"",(H9+I9+E9)/(1-D9-Parâmetros!$B$6-Parâmetros!$B$5)) -> 371.22302 | P9: =IF(M9<0,"PREJUÍZO",IF(N9<Parâmetros!$B$5,"ABAIXO DO PISO","OK")) -> OK
A10: MLB4728168353 | B10: Toldo Metal 290x70 | C10: Premium | D10: 0.135 | E10: 0 | F10: 590 | G10: 403.99 | H10: 311 | I10: 0 | J10: =G10*D10+E10 -> 54.53865 | K10: =G10*Parâmetros!$B$6 -> 20.1995 | L10: =J10+K10 -> 74.73815 | M10: =G10-L10-H10-I10 -> 18.25185 | N10: =IF(G10=0,0,M10/G10) -> 0.045178965 | O10: =IF((1-D10-Parâmetros!$B$6-Parâmetros!$B$5)<=0,"",(H10+I10+E10)/(1-D10-Parâmetros!$B$6-Parâmetros!$B$5)) -> 447.48201 | P10: =IF(M10<0,"PREJUÍZO",IF(N10<Parâmetros!$B$5,"ABAIXO DO PISO","OK")) -> ABAIXO DO PISO
A11: MLB6879345124 | B11: Toldo Metal 145x70 | C11: Premium | D11: 0.135 | E11: 0 | F11: 490 | G11: 280.99 | H11: 198 | I11: 0 | J11: =G11*D11+E11 -> 37.93365 | K11: =G11*Parâmetros!$B$6 -> 14.0495 | L11: =J11+K11 -> 51.98315 | M11: =G11-L11-H11-I11 -> 31.00685 | N11: =IF(G11=0,0,M11/G11) -> 0.11034859 | O11: =IF((1-D11-Parâmetros!$B$6-Parâmetros!$B$5)<=0,"",(H11+I11+E11)/(1-D11-Parâmetros!$B$6-Parâmetros!$B$5)) -> 284.89209 | P11: =IF(M11<0,"PREJUÍZO",IF(N11<Parâmetros!$B$5,"ABAIXO DO PISO","OK")) -> ABAIXO DO PISO
A12: MLB4728439145 | B12: Toldo Metal 365x70 | C12: Premium | D12: 0.135 | E12: 0 | F12: 690 | G12: 476.99 | H12: 368 | I12: 0 | J12: =G12*D12+E12 -> 64.39365 | K12: =G12*Parâmetros!$B$6 -> 23.8495 | L12: =J12+K12 -> 88.24315 | M12: =G12-L12-H12-I12 -> 20.74685 | N12: =IF(G12=0,0,M12/G12) -> 0.043495356 | O12: =IF((1-D12-Parâmetros!$B$6-Parâmetros!$B$5)<=0,"",(H12+I12+E12)/(1-D12-Parâmetros!$B$6-Parâmetros!$B$5)) -> 529.4964 | P12: =IF(M12<0,"PREJUÍZO",IF(N12<Parâmetros!$B$5,"ABAIXO DO PISO","OK")) -> ABAIXO DO PISO
A13: MLB4951921009 | B13: Rack New Aurora Pérola | C13: Clássico | D13: 0.115 | E13: 0 | F13: 897.99 | G13: 897.99 | H13: 274 | I13: 0 | J13: =G13*D13+E13 -> 103.26885 | K13: =G13*Parâmetros!$B$6 -> 44.8995 | L13: =J13+K13 -> 148.16835 | M13: =G13-L13-H13-I13 -> 475.82165 | N13: =IF(G13=0,0,M13/G13) -> 0.52987411 | O13: =IF((1-D13-Parâmetros!$B$6-Parâmetros!$B$5)<=0,"",(H13+I13+E13)/(1-D13-Parâmetros!$B$6-Parâmetros!$B$5)) -> 383.21678 | P13: =IF(M13<0,"PREJUÍZO",IF(N13<Parâmetros!$B$5,"ABAIXO DO PISO","OK")) -> OK
A14: MLB6887673448 | B14: Toldo 230x100 Madeira Bronze | C14: Clássico | D14: 0.115 | E14: 0 | F14: 1220 | G14: 890.99 | H14: 408 | I14: 0 | J14: =G14*D14+E14 -> 102.46385 | K14: =G14*Parâmetros!$B$6 -> 44.5495 | L14: =J14+K14 -> 147.01335 | M14: =G14-L14-H14-I14 -> 335.97665 | N14: =IF(G14=0,0,M14/G14) -> 0.3770824 | O14: =IF((1-D14-Parâmetros!$B$6-Parâmetros!$B$5)<=0,"",(H14+I14+E14)/(1-D14-Parâmetros!$B$6-Parâmetros!$B$5)) -> 570.62937 | P14: =IF(M14<0,"PREJUÍZO",IF(N14<Parâmetros!$B$5,"ABAIXO DO PISO","OK")) -> OK
A15: MLB4731310629 | B15: Toldo Shoplima 230x100 Preto | C15: Clássico | D15: 0.115 | E15: 0 | F15: 1220 | G15: 890.99 | H15: 408 | I15: 0 | J15: =G15*D15+E15 -> 102.46385 | K15: =G15*Parâmetros!$B$6 -> 44.5495 | L15: =J15+K15 -> 147.01335 | M15: =G15-L15-H15-I15 -> 335.97665 | N15: =IF(G15=0,0,M15/G15) -> 0.3770824 | O15: =IF((1-D15-Parâmetros!$B$6-Parâmetros!$B$5)<=0,"",(H15+I15+E15)/(1-D15-Parâmetros!$B$6-Parâmetros!$B$5)) -> 570.62937 | P15: =IF(M15<0,"PREJUÍZO",IF(N15<Parâmetros!$B$5,"ABAIXO DO PISO","OK")) -> OK
A16: MLB6926100860 | B16: Toldo 155x100 Madeira Bronze | C16: Clássico | D16: 0.115 | E16: 0 | F16: 922 | G16: 619.99 | H16: 288 | I16: 0 | J16: =G16*D16+E16 -> 71.29885 | K16: =G16*Parâmetros!$B$6 -> 30.9995 | L16: =J16+K16 -> 102.29835 | M16: =G16-L16-H16-I16 -> 229.69165 | N16: =IF(G16=0,0,M16/G16) -> 0.37047638 | O16: =IF((1-D16-Parâmetros!$B$6-Parâmetros!$B$5)<=0,"",(H16+I16+E16)/(1-D16-Parâmetros!$B$6-Parâmetros!$B$5)) -> 402.7972 | P16: =IF(M16<0,"PREJUÍZO",IF(N16<Parâmetros!$B$5,"ABAIXO DO PISO","OK")) -> OK
... A32: MLB4793450555 | B32: Mesa Alta Bistrô Tabaco | C32: Clássico | D32: 0.105 | E32: 0 | F32: 344.9 | G32: 245.99 | H32: 117.4 | I32: 0 | J32: =G32*D32+E32 -> 25.82895 | K32: =G32*Parâmetros!$B$6 -> 12.2995 | L32: =J32+K32 -> 38.12845 | M32: =G32-L32-H32-I32 -> 90.46155 | N32: =IF(G32=0,0,M32/G32) -> 0.36774483 | O32: =IF((1-D32-Parâmetros!$B$6-Parâmetros!$B$5)<=0,"",(H32+I32+E32)/(1-D32-Parâmetros!$B$6-Parâmetros!$B$5)) -> 161.93103 | P32: =IF(M32<0,"PREJUÍZO",IF(N32<Parâmetros!$B$5,"ABAIXO DO PISO","OK")) -> OK
B33: TOTAL / MÉDIA | J33: =SUM(J5:J32) -> 2459.9161 | K33: =SUM(K5:K32) -> 977.286 | L33: =SUM(L5:L32) -> 3437.2021 | M33: =SUM(M5:M32) -> 6478.1179 | N33: =IF(SUM(G5:G32)=0,0,SUM(M5:M32)/SUM(G5:G32)) -> 0.33143409
B35: Legenda
B36: Azul | C36: número medido ou informado — troque só se souber que mudou
B37: Amarelo | C37: PARA PREENCHER — o frete que o ML cobra do vendedor
B38: Preto | C38: fórmula, não edite
B39: Verde | C39: puxado da aba Parâmetros

Sheet Conferência
A1: Confira a conta à mão
A2: Uma linha da aba Precificação, aberta passo a passo. Troque o número em B4 para conferir outra.
A4: Linha a conferir (5 a 32) | B4: 16
A6: Anúncio | B6: =INDEX(Precificação!B:B,$B$4) -> Toldo 155x100 Madeira Bronze
A7: Preço de venda hoje | B7: =INDEX(Precificação!G:G,$B$4) -> 619.99
A8: Comissão do ML (%) | B8: =INDEX(Precificação!D:D,$B$4) -> 0.115
A9: Alíquota de imposto | B9: =Parâmetros!$B$6 -> 0.05
A10: Custo do produto | B10: =INDEX(Precificação!H:H,$B$4) -> 288
A11: Frete do vendedor | B11: =INDEX(Precificação!I:I,$B$4) -> 0
A13: A conta
A14: comissão em R$ | B14: =B7*B8 -> 71.29885 | C14: preço × comissão
A15: imposto em R$ | B15: =B7*B9 -> 30.9995 | C15: preço × alíquota — sobre o MESMO preço
A16: custo | B16: =B10 -> 288 | C16: da planilha do Ênio
A17: frete | B17: =B11 -> 0 | C17: a preencher
A18: sobra | B18: =B7-B14-B15-B16-B17 -> 229.69165 | C18: preço menos tudo acima
A19: margem | B19: =IF(B7=0,0,B18/B7) -> 0.37047638 | C19: sobra ÷ preço
A20: Bate com a aba Precificação? | B20: =IF(ABS(B18-INDEX(Precificação!$M$5:$M$32,$B$4-4))<0.01,"sim, confere","DIVERGE - me avise") -> sim, confere
A22: Por que somar os percentuais e não descontar um depois do outro
A24: somando: preço × (1 − 5% − 11,5%) = preço × 0,835
A25: em cascata: preço × 0,95 × 0,885 = preço × 0,84075
A27: A forma certa é somar. Os dois percentuais incidem sobre a MESMA base — o
A28: preço de venda cheio. O Mercado Livre cobra a comissão sobre o preço todo,
A29: e o imposto também é sobre o preço todo. Descontar em cascata faria o
A30: segundo percentual incidir sobre um valor já reduzido, o que não acontece.
A32: Por isso nenhuma fórmula desta planilha usa o resultado de outra taxa:
A33: a comissão é =G×D e o imposto é =G×5%, ambos partindo da coluna G.
